ml_optfit/__init__py
ml_optfit/ml_optfit.py
ml_optfit/nn_model_creation.py
ml_optfit-0.1.7.dist-info/METADATA
ml_optfit-0.1.7.dist-info/WHEEL
ml_optfit-0.1.7.dist-info/RECORD
